chemtrayzer-3.0.0b4.dist-info/METADATA
chemtrayzer-3.0.0b4.dist-info/WHEEL
chemtrayzer-3.0.0b4.dist-info/entry_points.txt
chemtrayzer-3.0.0b4.dist-info/licenses/LICENSE.md
chemtrayzer/__init__.py
chemtrayzer/core/__init__.py
chemtrayzer/core/_basissets.py
chemtrayzer/core/_bond_order.py
chemtrayzer/core/_serialization.py
chemtrayzer/core/chemid.py
chemtrayzer/core/constants.py
chemtrayzer/core/coords.py
chemtrayzer/core/database.py
chemtrayzer/core/graph.py
chemtrayzer/core/kinetics.py
chemtrayzer/core/lot.py
chemtrayzer/core/md.py
chemtrayzer/core/periodic_table.py
chemtrayzer/core/qm.py
chemtrayzer/core/testing.py
chemtrayzer/core/thermo.py
chemtrayzer/engine/__init__.py
chemtrayzer/engine/_event.py
chemtrayzer/engine/_pythonjob.py
chemtrayzer/engine/_serialization.py
chemtrayzer/engine/_submittable.py
chemtrayzer/engine/_workspace.py
chemtrayzer/engine/cmdtools.py
chemtrayzer/engine/config.py
chemtrayzer/engine/database.py
chemtrayzer/engine/errors.py
chemtrayzer/engine/investigation.py
chemtrayzer/engine/jobsystem.py
chemtrayzer/engine/testing.py
chemtrayzer/io/__init__.py
chemtrayzer/io/fileutils.py
chemtrayzer/io/sdf.py
chemtrayzer/jobs/__init__.py
chemtrayzer/jobs/ams.py
chemtrayzer/jobs/crest.py
chemtrayzer/jobs/gaussian.py
chemtrayzer/jobs/lammps.py
chemtrayzer/jobs/mess.py
chemtrayzer/jobs/orca.py
chemtrayzer/jobs/packmol.py
chemtrayzer/models/__init__.py
chemtrayzer/models/kinetic_fits.py
chemtrayzer/qm/__init__.py
chemtrayzer/qm/conformer.py
chemtrayzer/qm/species.py
chemtrayzer/qm/thermo.py
chemtrayzer/qm/ts.py
chemtrayzer/reaction_sampling/__init__.py
chemtrayzer/reaction_sampling/atomutils.py
chemtrayzer/reaction_sampling/reaction_detection.py
chemtrayzer/reaction_sampling/reaction_graphing.py
chemtrayzer/reaction_sampling/reaction_sampling_investigation.py
chemtrayzer/ui/__init__.py
chemtrayzer/ui/cli.py
chemtrayzer/ui/rxn_sampling.py
chemtrayzer-3.0.0b4.dist-info/RECORD
